[
  {
    "full_name": "LittleMouseGames/GodotAssetLibrary",
    "stargazers_count": 6,
    "open_issues_count": 7,
    "forks_count": 0
  },
  {
    "full_name": "fractureiser-investigation/fractureiser",
    "stargazers_count": 1121,
    "open_issues_count": 18,
    "forks_count": 81
  },
  {
    "full_name": "xCollateral/VulkanMod",
    "stargazers_count": 1078,
    "open_issues_count": 118,
    "forks_count": 84
  },
  {
    "full_name": "wgpu-mc/wgpu-mc",
    "stargazers_count": 376,
    "open_issues_count": 14,
    "forks_count": 27
  },
  {
    "full_name": "ndless-nspire/Ndless",
    "stargazers_count": 732,
    "open_issues_count": 62,
    "forks_count": 102
  },
  {
    "full_name": "NvChad/NvChad",
    "stargazers_count": 19307,
    "open_issues_count": 3,
    "forks_count": 1546
  },
  {
    "full_name": "keiwando/evolution",
    "stargazers_count": 326,
    "open_issues_count": 9,
    "forks_count": 52
  },
  {
    "full_name": "DiscordStyles/Fluent",
    "stargazers_count": 227,
    "open_issues_count": 14,
    "forks_count": 39
  },
  {
    "full_name": "PlainDevelopment/discord-bot-eco",
    "stargazers_count": 9,
    "open_issues_count": 0,
    "forks_count": 2
  },
  {
    "full_name": "hhhzzzsss/SongPlayer",
    "stargazers_count": 35,
    "open_issues_count": 6,
    "forks_count": 9
  },
  {
    "full_name": "victornpb/undiscord",
    "stargazers_count": 4286,
    "open_issues_count": 36,
    "forks_count": 714
  },
  {
    "full_name": "HorseNuggets/TerminatorPlus",
    "stargazers_count": 127,
    "open_issues_count": 15,
    "forks_count": 50
  },
  {
    "full_name": "Androz2091/discord-player",
    "stargazers_count": 544,
    "open_issues_count": 13,
    "forks_count": 185
  }
]